[
  {
    "_id": "58ebd22a6cd7351d4b711991",
    "index": 0,
    "guid": "b8bfab40-9e36-43a6-917a-cc1928611b09",
    "isActive": false,
    "balance": "$2,578.12",
    "picture": "http://placehold.it/32x32",
    "age": 25,
    "eyeColor": "brown",
    "name": {
      "first": "Hopper",
      "last": "Roman"
    },
    "company": "BRISTO",
    "email": "hopper.roman@bristo.info",
    "phone": "+1 (994) 586-2425",
    "address": "391 Broome Street, Troy, Connecticut, 195",
    "about": "Excepteur ex proident sint cillum aliqua et. Consectetur voluptate duis elit non. Eu Lorem occaecat aute do irure. Irure do non elit quis tempor voluptate. Non qui pariatur quis amet occaecat mollit non exercitation excepteur incididunt veniam. Ea ut ad laborum deserunt minim pariatur ipsum adipisicing in aute magna sit mollit.",
    "registered": "Wednesday, December 2, 2015 1:39 PM",
    "latitude": "22.799418",
    "longitude": "-115.144901",
    "tags": [
      "veniam",
      "voluptate",
      "irure",
      "amet",
      "sunt"
    ],
    "range": [
      0,
      1,
      2,
      3,
      4,
      5,
      6,
      7,
      8,
      9
    ],
    "friends": [
      {
        "id": 0,
        "name": "Cote Schultz"
      },
      {
        "id": 1,
        "name": "Earline Hewitt"
      },
      {
        "id": 2,
        "name": "Esther Dixon"
      }
    ],
    "greeting": "Hello, Hopper! You have 7 unread messages.",
    "favoriteFruit": "strawberry"
  },
  {
    "_id": "58ebd22aec01d7241d0e18be",
    "index": 1,
    "guid": "ecf32458-2014-4120-8c43-839433ed7f62",
    "isActive": true,
    "balance": "$3,727.02",
    "picture": "http://placehold.it/32x32",
    "age": 27,
    "eyeColor": "brown",
    "name": {
      "first": "Maude",
      "last": "Cruz"
    },
    "company": "VORATAK",
    "email": "maude.cruz@voratak.biz",
    "phone": "+1 (882) 580-2006",
    "address": "589 Rockaway Parkway, Rutherford, Federated States Of Micronesia, 1097",
    "about": "Amet cupidatat laboris eu enim. Ad incididunt eiusmod dolore aliquip elit qui eu eiusmod elit deserunt dolor nisi in Lorem. Anim culpa mollit officia aliqua dolore id officia ullamco Lorem. Fugiat magna magna reprehenderit ipsum magna sint ut.",
    "registered": "Tuesday, July 8, 2014 8:18 AM",
    "latitude": "-38.950632",
    "longitude": "-84.946128",
    "tags": [
      "reprehenderit",
      "laboris",
      "aliquip",
      "ipsum",
      "enim"
    ],
    "range": [
      0,
      1,
      2,
      3,
      4,
      5,
      6,
      7,
      8,
      9
    ],
    "friends": [
      {
        "id": 0,
        "name": "Effie Fitzgerald"
      },
      {
        "id": 1,
        "name": "Terry Payne"
      },
      {
        "id": 2,
        "name": "Cora Gallagher"
      }
    ],
    "greeting": "Hello, Maude! You have 10 unread messages.",
    "favoriteFruit": "apple"
  },
  {
    "_id": "58ebd22acbcd375de5e52842",
    "index": 2,
    "guid": "b8106f73-5cf1-4a2e-a46d-6a602133b88d",
    "isActive": true,
    "balance": "$2,386.29",
    "picture": "http://placehold.it/32x32",
    "age": 38,
    "eyeColor": "green",
    "name": {
      "first": "Greene",
      "last": "Davidson"
    },
    "company": "TECHMANIA",
    "email": "greene.davidson@techmania.net",
    "phone": "+1 (857) 591-3130",
    "address": "893 Independence Avenue, Osage, Washington, 5082",
    "about": "In anim incididunt ex ea est elit sunt sint irure sit ad. Ex incididunt consequat cupidatat Lorem. Deserunt nisi nostrud eiusmod velit occaecat sint laboris magna nisi nostrud qui reprehenderit elit deserunt. Ad dolore ipsum mollit excepteur. Reprehenderit mollit ipsum ipsum in velit quis nulla. Magna consequat enim fugiat et voluptate labore mollit nulla nulla et minim ullamco est pariatur. Ex elit veniam eu voluptate consequat duis cupidatat aute quis eu ea.",
    "registered": "Sunday, September 18, 2016 3:06 AM",
    "latitude": "2.629876",
    "longitude": "23.592862",
    "tags": [
      "tempor",
      "dolor",
      "ad",
      "nulla",
      "laborum"
    ],
    "range": [
      0,
      1,
      2,
      3,
      4,
      5,
      6,
      7,
      8,
      9
    ],
    "friends": [
      {
        "id": 0,
        "name": "Sosa Bright"
      },
      {
        "id": 1,
        "name": "Minnie Fowler"
      },
      {
        "id": 2,
        "name": "Hays Hayes"
      }
    ],
    "greeting": "Hello, Greene! You have 5 unread messages.",
    "favoriteFruit": "banana"
  },
  {
    "_id": "58ebd22a1d624add09a80057",
    "index": 3,
    "guid": "061edc08-b38a-45ed-9910-ab3af1502190",
    "isActive": true,
    "balance": "$1,617.91",
    "picture": "http://placehold.it/32x32",
    "age": 37,
    "eyeColor": "brown",
    "name": {
      "first": "Rivera",
      "last": "Barlow"
    },
    "company": "ZOLAREX",
    "email": "rivera.barlow@zolarex.name",
    "phone": "+1 (876) 416-3055",
    "address": "170 Hampton Place, Strong, Maine, 1945",
    "about": "Cupidatat nostrud pariatur cillum sint excepteur aliquip. Esse incididunt adipisicing pariatur non ipsum amet duis aute et. Labore sint eiusmod adipisicing in tempor ex consequat minim.",
    "registered": "Wednesday, September 30, 2015 12:42 PM",
    "latitude": "-37.849813",
    "longitude": "-116.227093",
    "tags": [
      "ut",
      "exercitation",
      "minim",
      "exercitation",
      "non"
    ],
    "range": [
      0,
      1,
      2,
      3,
      4,
      5,
      6,
      7,
      8,
      9
    ],
    "friends": [
      {
        "id": 0,
        "name": "Small Hamilton"
      },
      {
        "id": 1,
        "name": "Sandra Madden"
      },
      {
        "id": 2,
        "name": "Knox Foreman"
      }
    ],
    "greeting": "Hello, Rivera! You have 6 unread messages.",
    "favoriteFruit": "banana"
  },
  {
    "_id": "58ebd22a950794ab8c4e9148",
    "index": 4,
    "guid": "5a034881-fae4-40f8-a163-b75fc75bd0cc",
    "isActive": true,
    "balance": "$2,096.85",
    "picture": "http://placehold.it/32x32",
    "age": 23,
    "eyeColor": "green",
    "name": {
      "first": "Cristina",
      "last": "Klein"
    },
    "company": "VORTEXACO",
    "email": "cristina.klein@vortexaco.ca",
    "phone": "+1 (950) 533-3512",
    "address": "164 Baltic Street, Sylvanite, West Virginia, 5347",
    "about": "Cupidatat sint officia esse amet qui quis. Labore voluptate id ea deserunt nisi irure culpa ipsum eiusmod commodo occaecat sint. Ex enim sint sunt quis eiusmod occaecat in ad tempor cillum eiusmod nisi. Aute irure id ex dolor ipsum fugiat id aliqua adipisicing cillum adipisicing nisi. Elit est Lorem commodo non tempor nulla mollit quis consectetur. Deserunt do nisi consectetur reprehenderit Lorem quis do magna velit. Magna commodo incididunt aliqua aute commodo qui deserunt.",
    "registered": "Sunday, May 4, 2014 7:37 AM",
    "latitude": "-26.256179",
    "longitude": "170.183685",
    "tags": [
      "irure",
      "pariatur",
      "elit",
      "do",
      "id"
    ],
    "range": [
      0,
      1,
      2,
      3,
      4,
      5,
      6,
      7,
      8,
      9
    ],
    "friends": [
      {
        "id": 0,
        "name": "Hardin Dennis"
      },
      {
        "id": 1,
        "name": "Edna Mcgowan"
      },
      {
        "id": 2,
        "name": "Hollie Frank"
      }
    ],
    "greeting": "Hello, Cristina! You have 8 unread messages.",
    "favoriteFruit": "apple"
  },
  {
    "_id": "58ebd22ae105f9a3e95d68c9",
    "index": 5,
    "guid": "d5f07e2d-b31c-4c97-b0c1-023c889fe1c2",
    "isActive": true,
    "balance": "$2,460.27",
    "picture": "http://placehold.it/32x32",
    "age": 34,
    "eyeColor": "green",
    "name": {
      "first": "Vicki",
      "last": "Holloway"
    },
    "company": "CHORIZON",
    "email": "vicki.holloway@chorizon.biz",
    "phone": "+1 (810) 531-2420",
    "address": "126 Milton Street, Lafferty, Palau, 9294",
    "about": "Elit id ad ullamco et consectetur elit nostrud anim. Pariatur dolore proident excepteur elit aute nisi excepteur. Incididunt eiusmod in non qui officia veniam ex officia laborum sunt ullamco consequat. Deserunt labore nisi elit adipisicing aute ea amet. Reprehenderit laboris voluptate ut nostrud nulla commodo officia cupidatat consectetur magna tempor ipsum minim nisi. Est elit aute consectetur quis cupidatat elit deserunt mollit.",
    "registered": "Saturday, February 15, 2014 4:44 PM",
    "latitude": "-24.977162",
    "longitude": "139.15458",
    "tags": [
      "officia",
      "dolor",
      "ipsum",
      "commodo",
      "voluptate"
    ],
    "range": [
      0,
      1,
      2,
      3,
      4,
      5,
      6,
      7,
      8,
      9
    ],
    "friends": [
      {
        "id": 0,
        "name": "Muriel Lowe"
      },
      {
        "id": 1,
        "name": "Weeks Dunn"
      },
      {
        "id": 2,
        "name": "Kris Buck"
      }
    ],
    "greeting": "Hello, Vicki! You have 8 unread messages.",
    "favoriteFruit": "banana"
  },
  {
    "_id": "58ebd22a129ee39e181b1e4a",
    "index": 6,
    "guid": "4d8e3e69-c3af-489c-8fb5-478f0edcf02b",
    "isActive": false,
    "balance": "$3,314.78",
    "picture": "http://placehold.it/32x32",
    "age": 28,
    "eyeColor": "green",
    "name": {
      "first": "Norton",
      "last": "Joseph"
    },
    "company": "ISOTERNIA",
    "email": "norton.joseph@isoternia.co.uk",
    "phone": "+1 (921) 510-3133",
    "address": "479 Gates Avenue, Sterling, American Samoa, 8216",
    "about": "Ut fugiat ea minim minim veniam officia magna nostrud laboris occaecat quis minim officia voluptate. Mollit aliquip culpa ut excepteur minim sit dolore nulla. Eu laborum excepteur commodo anim incididunt aute eiusmod aute mollit sint qui pariatur cupidatat amet. Ex ut elit eiusmod et veniam sit dolor fugiat sunt ut qui officia ipsum. Nisi fugiat deserunt eu cillum reprehenderit mollit nisi magna culpa magna est reprehenderit incididunt. Dolor commodo elit commodo cupidatat enim dolore ad labore voluptate officia commodo. Irure excepteur proident cillum sit.",
    "registered": "Saturday, October 22, 2016 6:46 AM",
    "latitude": "24.110854",
    "longitude": "-88.254043",
    "tags": [
      "qui",
      "qui",
      "ex",
      "amet",
      "sit"
    ],
    "range": [
      0,
      1,
      2,
      3,
      4,
      5,
      6,
      7,
      8,
      9
    ],
    "friends": [
      {
        "id": 0,
        "name": "Burke Jennings"
      },
      {
        "id": 1,
        "name": "Emily Morgan"
      },
      {
        "id": 2,
        "name": "Stuart Shepard"
      }
    ],
    "greeting": "Hello, Norton! You have 7 unread messages.",
    "favoriteFruit": "apple"
  }
]